{"ads":{
  
  "show_dialog":"non",
  "button_text":"start",
  "image_backg":"https://bitboycrypto.com/wp-content/uploads/2023/08/screen-shot-2023-08-27-at-9.38.11-am.png",
  "icon":"https://bitboycrypto.com/wp-content/uploads/2022/06/bitboy_crypto_logo-orange.png",
  "main_text1":"Connecting \nWeb3",
  "main_text2":"The commmunications protocol for Web3, BitBoy Crypto brings the ecosystem together by enabling wallets and apps to securely connect and interact."
},
 
 "my_data":[
  {"title":"title1",
  "download_num":"58458",
  "visite_num":"2141",
  "photo":"https://www.gamerevolution.com/wp-content/uploads/sites/2/2019/02/fortnite4.jpg"},
  {"title":"title2 ser",
  "download_num":"58458",
  "visite_num":"2141",
  "photo":"https://www.gamerevolution.com/wp-content/uploads/sites/2/2019/02/fortnite4.jpg"},
  {"title":"title3 ser",
  "download_num":"58458",
  "visite_num":"2141",
  "photo":"https://www.gamerevolution.com/wp-content/uploads/sites/2/2019/02/fortnite4.jpg"},
  {"title":"title4 ser",
  "download_num":"58458",
  "visite_num":"2141",
  "photo":"https://www.gamerevolution.com/wp-content/uploads/sites/2/2019/02/fortnite4.jpg"},
  {"title":"title5 ser",
  "download_num":"58458",
  "visite_num":"2141",
  "photo":"https://www.gamerevolution.com/wp-content/uploads/sites/2/2019/02/fortnite4.jpg"},
  {"title":"title6 ser",
  "download_num":"58458",
  "visite_num":"2141",
  "photo":"https://www.gamerevolution.com/wp-content/uploads/sites/2/2019/02/fortnite4.jpg"},
  {"title":"title7 ser",
  "download_num":"58458",
  "visite_num":"2141",
  "photo":"https://www.gamerevolution.com/wp-content/uploads/sites/2/2019/02/fortnite4.jpg"},
  {"title":"title8 ser",
  "download_num":"58458",
  "visite_num":"2141",
  "photo":"https://www.gamerevolution.com/wp-content/uploads/sites/2/2019/02/fortnite4.jpg"}
   ]
  

}
   
