{
    "Ads": {
        "ShowAds": true,
        "ShowLoadingAds": true,
        "ClickCount": 1,
        "PriorityBanner": "max",
        "priorityInterstitial": "max",
        "PriorityNative": "max",
        "PriorityReward": "max",
        "IronAppKey": "1c33c0215",
        "IronBanner": "DefaultBanner",
        "IronInterstitial": "DefaultInterstitial",
        "IronReward": "DefaultRewardedVideo",
        "TopOnAppKey": "xxxxxxxx",
        "TopOnAppID": "xxxxxxxx",
        "TopOnBanner": "xxxxxxxx",
        "TopOnInterstitial": "xxxxxxxx",
        "TopOnNative": "xxxxxxxx",
        "TopOnReward": "xxxxxxxx",
        "MaxBanner": "29c514ae8f21ce41",
        "MaxInterstitial": "13d5de7a00d48501",
        "MaxNative": "53ae49d215c890c7",
        "MaxReward": "f70a8c6e8abddec5",
        "FanBanner": "xxxxx",
        "FanInterstitial": "xxxxx",
        "FanNative": "xxxxxx"
    },
    "ControlApp": {
        "ShowFootballScoresWarning": false,
        "ShowCricketSCoresWarning": false,
        "PlayerPackageName": "com.videoplayer.krcplayerhdfree",
        "OnesignalID": "xxxxx",
        "ShowUpdate": true,
        "UpdateVersion": 2,
        "UpdateLink": "https://play.google.com/store/apps/details?id=com.livefootballtv.allfootball_livetvhd2023"
    }
}
